{
    "joystick": {
        "center": [593, 1047],
        "radius": 200
    },
    "attack":[2832,1273],
    "Jump_Back":[2631,1290],
    "Jump":[2941,1133],
    "Roulette":[2842,966],
    "skill4":[2324,1132],
    "skill7":[2036,1294],
    "skill1": [2430,1294],
    "skill10": [1621,1289],
    "skill5":[2237,1294],
    "skill3":[2723,1132],
    "skill2":[2520,1132],
    "skill6":[2123,1132],
    "skill8":[1335,1289],
    "skill11":[1773,1289],
    "skill9":[1478,1289],
    "skill12":"left",
    "skill13":"up",
    "skill14":"right",
    "skill15":[1554,194]
}